nlm_ingestor/__init__.py
nlm_ingestor/file_parser/__init__.py
nlm_ingestor/file_parser/file_parser.py
nlm_ingestor/file_parser/markdown_parser.py
nlm_ingestor/file_parser/parser_factory.py
nlm_ingestor/file_parser/tika_parser.py
nlm_ingestor/ingestion_daemon/__init__.py
nlm_ingestor/ingestion_daemon/__main__.py
nlm_ingestor/ingestion_daemon/config.py
nlm_ingestor/ingestor/__init__.py
nlm_ingestor/ingestor/block.py
nlm_ingestor/ingestor/data_loader.py
nlm_ingestor/ingestor/formatter.py
nlm_ingestor/ingestor/html_ingestor.py
nlm_ingestor/ingestor/ingestor_api.py
nlm_ingestor/ingestor/line_parser.py
nlm_ingestor/ingestor/patterns.py
nlm_ingestor/ingestor/pdf_ingestor.py
nlm_ingestor/ingestor/processors.py
nlm_ingestor/ingestor/processors_utils.py
nlm_ingestor/ingestor/sec_html_ingestor.py
nlm_ingestor/ingestor/styling_utils.py
nlm_ingestor/ingestor/table_builder.py
nlm_ingestor/ingestor/table_parser.py
nlm_ingestor/ingestor/text_ingestor.py
nlm_ingestor/ingestor/xml_ingestor.py
nlm_ingestor/ingestor/visual_ingestor/__init__.py
nlm_ingestor/ingestor/visual_ingestor/block_renderer.py
nlm_ingestor/ingestor/visual_ingestor/indent_parser.py
nlm_ingestor/ingestor/visual_ingestor/new_indent_parser.py
nlm_ingestor/ingestor/visual_ingestor/order_fixer.py
nlm_ingestor/ingestor/visual_ingestor/style_utils.py
nlm_ingestor/ingestor/visual_ingestor/table_parser.py
nlm_ingestor/ingestor/visual_ingestor/vi_helper_utils.py
nlm_ingestor/ingestor/visual_ingestor/visual_ingestor.py
nlm_ingestor/ingestor_models/__init__.py
nlm_ingestor/ingestor_models/symspell/__init__.py
nlm_ingestor/ingestor_utils/__init__.py
nlm_ingestor/ingestor_utils/de_duplicate_engine.py
nlm_ingestor/ingestor_utils/ing_named_tuples.py
nlm_ingestor/ingestor_utils/lru_cache.py
nlm_ingestor/ingestor_utils/ner_dict.py
nlm_ingestor/ingestor_utils/objects.py
nlm_ingestor/ingestor_utils/parsing_utils.py
nlm_ingestor/ingestor_utils/spell_utils.py
nlm_ingestor/ingestor_utils/utils.py
nlm_ingestor-0.1.7.dist-info/LICENSE.txt
nlm_ingestor-0.1.7.dist-info/METADATA
nlm_ingestor-0.1.7.dist-info/NOTICE.txt
nlm_ingestor-0.1.7.dist-info/WHEEL
nlm_ingestor-0.1.7.dist-info/top_level.txt
nlm_ingestor-0.1.7.dist-info/RECORD
