Metadata-Version: 2.1
Name: nlm-ingestor
Version: 0.1.7
Summary: Parsers and ingestors for different file types and formats
Home-page: https://github.com/nlmatics/nlm-ingestor
Author: Ambika Sukla
Author-email: ambika.sukla@nlmatics.com
License: Apache License 2.0
Classifier: Development Status :: 5 - Production/Stable
Classifier: Development Status :: 1 - Planning
Classifier: Intended Audience :: Science/Research
Classifier: Intended Audience :: Developers
Classifier: Intended Audience :: Legal Industry
Classifier: License :: OSI Approved :: Apache Software License
Classifier: Operating System :: POSIX :: Linux
Classifier: Programming Language :: Python :: 3 :: Only
License-File: LICENSE.txt
License-File: NOTICE.txt
Requires-Dist: flask
Requires-Dist: flask-restful
Requires-Dist: flask-jsonpify
Requires-Dist: gunicorn
Requires-Dist: werkzeug
Requires-Dist: tika
Requires-Dist: bs4
Requires-Dist: nltk
Requires-Dist: python-magic
Requires-Dist: numpy
Requires-Dist: tqdm
Requires-Dist: symspellpy >=6.7.0
Requires-Dist: pandas >=1.2.4
Requires-Dist: mistune ==2.0.3
Requires-Dist: lxml ==4.9.1
Requires-Dist: unidecode
Requires-Dist: nlm-utils
